compact_binary_protocol/__init__.py
compact_binary_protocol/data/__init__.py
compact_binary_protocol/data/constants.py
compact_binary_protocol/data/customer_id.py
compact_binary_protocol/data/device_status.py
compact_binary_protocol/data/environment.py
compact_binary_protocol/data/kv.py
compact_binary_protocol/data/location.py
compact_binary_protocol/data/multi.py
compact_binary_protocol/data/network_info.py
compact_binary_protocol/data/null.py
compact_binary_protocol/data/steps.py
compact_binary_protocol/data/versions.py
compact_binary_protocol/decoders/__init__.py
compact_binary_protocol/decoders/data_reader.py
compact_binary_protocol/decoders/packet_decoder.py
compact_binary_protocol/encodings/__init__.py
compact_binary_protocol/encodings/var_string.py
compact_binary_protocol/packets/__init__.py
compact_binary_protocol/packets/base.py
compact_binary_protocol/packets/config.py
compact_binary_protocol/packets/telemetry.py
compact_binary_protocol-0.3.0.dist-info/METADATA
compact_binary_protocol-0.3.0.dist-info/WHEEL
compact_binary_protocol-0.3.0.dist-info/top_level.txt
compact_binary_protocol-0.3.0.dist-info/RECORD
