Metadata-Version: 2.4
Name: compact-binary-protocol
Version: 0.3.0
Summary: A library implementing a compact binary protocol
Author-email: "Tartabit, LLC" <support@tartabit.com>
License: MIT
Project-URL: Homepage, https://github.com/tartabit/compact-binary-protocol
Classifier: Programming Language :: Python :: 3
Classifier: License :: OSI Approved :: MIT License
Classifier: Operating System :: OS Independent
Requires-Python: >=3.6
Requires-Dist: requests
